pyvesync/__init__.py
pyvesync/auth.py
pyvesync/const.py
pyvesync/device_container.py
pyvesync/device_map.py
pyvesync/py.typed
pyvesync/vesync.py
pyvesync/vesynchome.py
pyvesync/base_devices/__init__.py
pyvesync/base_devices/bulb_base.py
pyvesync/base_devices/fan_base.py
pyvesync/base_devices/fryer_base.py
pyvesync/base_devices/humidifier_base.py
pyvesync/base_devices/outlet_base.py
pyvesync/base_devices/purifier_base.py
pyvesync/base_devices/switch_base.py
pyvesync/base_devices/thermostat_base.py
pyvesync/base_devices/vesyncbasedevice.py
pyvesync/devices/__init__.py
pyvesync/devices/vesyncbulb.py
pyvesync/devices/vesyncfan.py
pyvesync/devices/vesynchumidifier.py
pyvesync/devices/vesynckitchen.py
pyvesync/devices/vesyncoutlet.py
pyvesync/devices/vesyncpurifier.py
pyvesync/devices/vesyncswitch.py
pyvesync/devices/vesyncthermostat.py
pyvesync/models/__init__.py
pyvesync/models/base_models.py
pyvesync/models/bulb_models.py
pyvesync/models/bypass_models.py
pyvesync/models/fan_models.py
pyvesync/models/fryer_models.py
pyvesync/models/home_models.py
pyvesync/models/humidifier_models.py
pyvesync/models/outlet_models.py
pyvesync/models/purifier_models.py
pyvesync/models/switch_models.py
pyvesync/models/thermostat_models.py
pyvesync/models/vesync_models.py
pyvesync/utils/__init__.py
pyvesync/utils/colors.py
pyvesync/utils/device_mixins.py
pyvesync/utils/enum_utils.py
pyvesync/utils/errors.py
pyvesync/utils/helpers.py
pyvesync/utils/logs.py
pyvesync-3.4.1.dist-info/licenses/LICENSE
pyvesync-3.4.1.dist-info/METADATA
pyvesync-3.4.1.dist-info/WHEEL
pyvesync-3.4.1.dist-info/top_level.txt
pyvesync-3.4.1.dist-info/RECORD
