Metadata-Version: 2.4
Name: pyvesync
Version: 3.4.1
Summary: pyvesync is a library to manage Etekcity Devices, Cosori Air Fryers, and Levoit Air Purifiers run on the VeSync app.
Author: Mark Perdue
Author-email: Joe Trabulsy <webdjoe@gmail.com>
License: MIT
Project-URL: Home Page, https://github.com/webdjoe/pyvesync
Project-URL: Documentation, https://webdjoe.github.io/pyvesync/latest/
Keywords: iot,vesync,levoit,etekcity,cosori,valceno
Classifier: License :: OSI Approved :: MIT License
Classifier: Intended Audience :: Developers
Classifier: Natural Language :: English
Classifier: Topic :: Home Automation
Requires-Python: >=3.11
License-File: LICENSE
Requires-Dist: aiohttp>=3.8.1
Requires-Dist: mashumaro[orjson]>=3.13.1
Provides-Extra: dev
Requires-Dist: pytest; extra == "dev"
Requires-Dist: pytest-cov; extra == "dev"
Requires-Dist: pyyaml; extra == "dev"
Requires-Dist: pylint; extra == "dev"
Requires-Dist: mypy; extra == "dev"
Requires-Dist: ruff; extra == "dev"
Requires-Dist: pre-commit; extra == "dev"
Requires-Dist: tox; extra == "dev"
Requires-Dist: requests; extra == "dev"
Requires-Dist: aiofiles; extra == "dev"
Provides-Extra: docs
Requires-Dist: mkdocstrings-python; extra == "docs"
Requires-Dist: mkdocs; extra == "docs"
Requires-Dist: ruff; extra == "docs"
Requires-Dist: Pygments; extra == "docs"
Requires-Dist: mkdocs-material; extra == "docs"
Requires-Dist: mkdocstrings; extra == "docs"
Requires-Dist: mkdocs-include-markdown-plugin; extra == "docs"
Requires-Dist: mkdocs-material-extensions; extra == "docs"
Requires-Dist: pymdown-extensions; extra == "docs"
Requires-Dist: mike; extra == "docs"
Requires-Dist: mkdocs-git-revision-date-localized-plugin; extra == "docs"
Requires-Dist: docstring-inheritance; extra == "docs"
Requires-Dist: mkdocs-autorefs; extra == "docs"
Requires-Dist: griffe-inherited-docstrings; extra == "docs"
Requires-Dist: griffe_warnings_deprecated; extra == "docs"
Dynamic: license-file
